prattle/__init__.py
prattle-0.1.dist-info/METADATA
prattle-0.1.dist-info/RECORD
prattle-0.1.dist-info/WHEEL
prattle-0.1.dist-info/top_level.txt
