Metadata-Version: 2.1
Name: prattle
Version: 0.1
Summary: A scuttlebutt bridge written in Tornado.
Home-page: https://github.com/supakeen/prattle
Author: supakeen
Author-email: cmdr@supakeen.com
License: UNKNOWN
Platform: UNKNOWN
Requires-Dist: scuttlebutt
Requires-Dist: tornado
